sequence_metrics/__init__.py
sequence_metrics/metrics.py
sequence_metrics/testing.py
sequence_metrics/wandb_tools.py
sequence_metrics-0.1.5.dist-info/METADATA
sequence_metrics-0.1.5.dist-info/WHEEL
sequence_metrics-0.1.5.dist-info/licenses/LICENSE
sequence_metrics-0.1.5.dist-info/RECORD
