Metadata-Version: 2.4
Name: sequence-metrics
Version: 0.1.5
Summary: A set of metrics for Sequence Labelling tasks
License-File: LICENSE
Author: Indico Data
Author-email: rd@indicodata.ai
Requires-Python: >=3.10,<3.14
Classifier: Programming Language :: Python :: 3
Classifier: Programming Language :: Python :: 3.10
Classifier: Programming Language :: Python :: 3.11
Classifier: Programming Language :: Python :: 3.12
Classifier: Programming Language :: Python :: 3.13
Requires-Dist: numpy
Requires-Dist: pandas
Requires-Dist: scikit-learn (>=1.0.0,<2.0.0)
Requires-Dist: spacy (>=3.8.7,<3.9)
Requires-Dist: tabulate
Requires-Dist: wandb
